volttron/utils/__init__.py
volttron/utils/argparser.py
volttron/utils/certs.py
volttron/utils/commands.py
volttron/utils/context.py
volttron/utils/file_access.py
volttron/utils/filewatch.py
volttron/utils/frame_serialization.py
volttron/utils/frozendict.py
volttron/utils/identities.py
volttron/utils/jsonapi.py
volttron/utils/jsonrpc.py
volttron/utils/keystore.py
volttron/utils/logging.py
volttron/utils/messagebus.py
volttron/utils/network.py
volttron/utils/persistance.py
volttron/utils/scheduling.py
volttron/utils/socket.py
volttron/utils/storeutils.py
volttron/utils/time.py
volttron_utils-0.3.4.dist-info/AUTHORS
volttron_utils-0.3.4.dist-info/METADATA
volttron_utils-0.3.4.dist-info/WHEEL
volttron_utils-0.3.4.dist-info/top_level.txt
volttron_utils-0.3.4.dist-info/RECORD
