Metadata-Version: 2.1
Name: volttron-utils
Version: 0.3.4
Summary: Utility classes and methods for VOLTTRON
Home-page: UNKNOWN
Author: The VOLTTRON Team
Author-email: volttron@pnnl.gov
License: Apache 2
Project-URL: Bug Reports, https://github.com/VOLTTRON/volttron-utils/issues
Project-URL: Source, https://github.com/VOLTTRON/volttron-utils/
Keywords: volttron, zmq, utilities
Platform: UNKNOWN
Classifier: Development Status :: 3 - Alpha
Classifier: Intended Audience :: Developers
Classifier: Intended Audience :: Science/Research
Classifier: Topic :: Home Automation
Classifier: Topic :: Software Development :: Embedded Systems
Classifier: License :: OSI Approved :: Apache Software License
Classifier: Programming Language :: Python :: 3.8
Classifier: Programming Language :: Python :: 3.9
Requires-Python: >=3.7, <4
License-File: AUTHORS
Requires-Dist: asn1crypto (==1.4.0)
Requires-Dist: cffi (==1.15.0)
Requires-Dist: cryptography (==2.3)
Requires-Dist: dateutils (==0.6.12)
Requires-Dist: gevent (==20.6.1)
Requires-Dist: idna (==3.3)
Requires-Dist: pbr (==5.8.0)
Requires-Dist: psutil (==5.8.0)
Requires-Dist: pycparser (==2.21)
Requires-Dist: pyopenssl (==19.0.0)
Requires-Dist: python-dateutil (==2.8.2)
Requires-Dist: pytz (==2021.3)
Requires-Dist: pyyaml (==6.0)
Requires-Dist: pyzmq (==22.3.0)
Requires-Dist: six (==1.16.0)
Requires-Dist: tzlocal (==2.1)
Requires-Dist: watchdog-gevent (==0.1.1)
Requires-Dist: watchdog (==2.1.6)
Requires-Dist: zmq (==0.0.0)
Requires-Dist: zope.event (==4.5.0)
Requires-Dist: zope.interface (==5.4.0)
Requires-Dist: greenlet (==0.4.16) ; (platform_python_implementation == 'CPython')
